{
  "openapi": "3.0.1",
  "info": {
    "title": "EduBrain",
    "version": "1.0"
  },
  "paths": {
    "/api/Club/getallclubs": {
      "get": {
        "tags": [
          "Club"
        ],
        "responses": {
          "200": {
            "description": "Success"
          }
        }
      }
    },
    "/api/Club/getclubbyid/{id}": {
      "get": {
        "tags": [
          "Club"
        ],
        "parameters": [
          {
            "name": "id",
            "in": "path",
            "required": true,
            "schema": {
              "type": "integer",
              "format": "int32"
            }
          }
        ],
        "responses": {
          "200": {
            "description": "Success"
          }
        }
      }
    },
    "/api/Club/addclubs": {
      "post": {
        "tags": [
          "Club"
        ],
        "requestBody": {
          "content": {
            "application/json": {
              "schema": {
                "$ref": "#/components/schemas/Club"
              }
            },
            "text/json": {
              "schema": {
                "$ref": "#/components/schemas/Club"
              }
            },
            "application/*+json": {
              "schema": {
                "$ref": "#/components/schemas/Club"
              }
            }
          }
        },
        "responses": {
          "200": {
            "description": "Success"
          }
        }
      }
    },
    "/api/Club/updateclub/{id}": {
      "put": {
        "tags": [
          "Club"
        ],
        "parameters": [
          {
            "name": "id",
            "in": "path",
            "required": true,
            "schema": {
              "type": "integer",
              "format": "int32"
            }
          }
        ],
        "requestBody": {
          "content": {
            "application/json": {
              "schema": {
                "$ref": "#/components/schemas/Club"
              }
            },
            "text/json": {
              "schema": {
                "$ref": "#/components/schemas/Club"
              }
            },
            "application/*+json": {
              "schema": {
                "$ref": "#/components/schemas/Club"
              }
            }
          }
        },
        "responses": {
          "200": {
            "description": "Success"
          }
        }
      }
    },
    "/api/Club/deleteclub/{id}": {
      "delete": {
        "tags": [
          "Club"
        ],
        "parameters": [
          {
            "name": "id",
            "in": "path",
            "required": true,
            "schema": {
              "type": "integer",
              "format": "int32"
            }
          }
        ],
        "responses": {
          "200": {
            "description": "Success"
          }
        }
      }
    },
    "/api/Department/getalldepartments": {
      "get": {
        "tags": [
          "Department"
        ],
        "responses": {
          "200": {
            "description": "Success"
          }
        }
      }
    },
    "/api/Department/getdepartmentbyid/{id}": {
      "get": {
        "tags": [
          "Department"
        ],
        "parameters": [
          {
            "name": "id",
            "in": "path",
            "required": true,
            "schema": {
              "type": "integer",
              "format": "int32"
            }
          }
        ],
        "responses": {
          "200": {
            "description": "Success"
          }
        }
      }
    },
    "/api/Department/adddepartments": {
      "post": {
        "tags": [
          "Department"
        ],
        "requestBody": {
          "content": {
            "application/json": {
              "schema": {
                "$ref": "#/components/schemas/Department"
              }
            },
            "text/json": {
              "schema": {
                "$ref": "#/components/schemas/Department"
              }
            },
            "application/*+json": {
              "schema": {
                "$ref": "#/components/schemas/Department"
              }
            }
          }
        },
        "responses": {
          "200": {
            "description": "Success"
          }
        }
      }
    },
    "/api/Department/updatedepartment/{id}": {
      "put": {
        "tags": [
          "Department"
        ],
        "parameters": [
          {
            "name": "id",
            "in": "path",
            "required": true,
            "schema": {
              "type": "integer",
              "format": "int32"
            }
          }
        ],
        "requestBody": {
          "content": {
            "application/json": {
              "schema": {
                "$ref": "#/components/schemas/Department"
              }
            },
            "text/json": {
              "schema": {
                "$ref": "#/components/schemas/Department"
              }
            },
            "application/*+json": {
              "schema": {
                "$ref": "#/components/schemas/Department"
              }
            }
          }
        },
        "responses": {
          "200": {
            "description": "Success"
          }
        }
      }
    },
    "/api/Department/deletedepartment/{id}": {
      "delete": {
        "tags": [
          "Department"
        ],
        "parameters": [
          {
            "name": "id",
            "in": "path",
            "required": true,
            "schema": {
              "type": "integer",
              "format": "int32"
            }
          }
        ],
        "responses": {
          "200": {
            "description": "Success"
          }
        }
      }
    },
    "/api/Employee/getallemployees": {
      "get": {
        "tags": [
          "Employee"
        ],
        "responses": {
          "200": {
            "description": "Success"
          }
        }
      }
    },
    "/api/Employee/getemployeebyid/{id}": {
      "get": {
        "tags": [
          "Employee"
        ],
        "parameters": [
          {
            "name": "id",
            "in": "path",
            "required": true,
            "schema": {
              "type": "integer",
              "format": "int32"
            }
          }
        ],
        "responses": {
          "200": {
            "description": "Success"
          }
        }
      }
    },
    "/api/Employee/addemployee": {
      "post": {
        "tags": [
          "Employee"
        ],
        "requestBody": {
          "content": {
            "application/json": {
              "schema": {
                "$ref": "#/components/schemas/EmployeeDto"
              }
            },
            "text/json": {
              "schema": {
                "$ref": "#/components/schemas/EmployeeDto"
              }
            },
            "application/*+json": {
              "schema": {
                "$ref": "#/components/schemas/EmployeeDto"
              }
            }
          }
        },
        "responses": {
          "200": {
            "description": "Success"
          }
        }
      }
    },
    "/api/Employee/updateemployee/{id}": {
      "put": {
        "tags": [
          "Employee"
        ],
        "parameters": [
          {
            "name": "id",
            "in": "path",
            "required": true,
            "schema": {
              "type": "integer",
              "format": "int32"
            }
          }
        ],
        "requestBody": {
          "content": {
            "application/json": {
              "schema": {
                "$ref": "#/components/schemas/EmployeeDto"
              }
            },
            "text/json": {
              "schema": {
                "$ref": "#/components/schemas/EmployeeDto"
              }
            },
            "application/*+json": {
              "schema": {
                "$ref": "#/components/schemas/EmployeeDto"
              }
            }
          }
        },
        "responses": {
          "200": {
            "description": "Success"
          }
        }
      }
    },
    "/api/Employee/deleteemployee/{id}": {
      "delete": {
        "tags": [
          "Employee"
        ],
        "parameters": [
          {
            "name": "id",
            "in": "path",
            "required": true,
            "schema": {
              "type": "integer",
              "format": "int32"
            }
          }
        ],
        "responses": {
          "200": {
            "description": "Success"
          }
        }
      }
    },
    "/api/EmployeeCategory/getallemployeecategories": {
      "get": {
        "tags": [
          "EmployeeCategory"
        ],
        "responses": {
          "200": {
            "description": "Success"
          }
        }
      }
    },
    "/api/EmployeeCategory/getemployeecategorybyid/{id}": {
      "get": {
        "tags": [
          "EmployeeCategory"
        ],
        "parameters": [
          {
            "name": "id",
            "in": "path",
            "required": true,
            "schema": {
              "type": "integer",
              "format": "int32"
            }
          }
        ],
        "responses": {
          "200": {
            "description": "Success"
          }
        }
      }
    },
    "/api/EmployeeCategory/addemployeecategories": {
      "post": {
        "tags": [
          "EmployeeCategory"
        ],
        "requestBody": {
          "content": {
            "application/json": {
              "schema": {
                "$ref": "#/components/schemas/EmployeeCategory"
              }
            },
            "text/json": {
              "schema": {
                "$ref": "#/components/schemas/EmployeeCategory"
              }
            },
            "application/*+json": {
              "schema": {
                "$ref": "#/components/schemas/EmployeeCategory"
              }
            }
          }
        },
        "responses": {
          "200": {
            "description": "Success"
          }
        }
      }
    },
    "/api/EmployeeCategory/updateemployeecategory/{id}": {
      "put": {
        "tags": [
          "EmployeeCategory"
        ],
        "parameters": [
          {
            "name": "id",
            "in": "path",
            "required": true,
            "schema": {
              "type": "integer",
              "format": "int32"
            }
          }
        ],
        "requestBody": {
          "content": {
            "application/json": {
              "schema": {
                "$ref": "#/components/schemas/EmployeeCategory"
              }
            },
            "text/json": {
              "schema": {
                "$ref": "#/components/schemas/EmployeeCategory"
              }
            },
            "application/*+json": {
              "schema": {
                "$ref": "#/components/schemas/EmployeeCategory"
              }
            }
          }
        },
        "responses": {
          "200": {
            "description": "Success"
          }
        }
      }
    },
    "/api/EmployeeCategory/deleteemployeecategory/{id}": {
      "delete": {
        "tags": [
          "EmployeeCategory"
        ],
        "parameters": [
          {
            "name": "id",
            "in": "path",
            "required": true,
            "schema": {
              "type": "integer",
              "format": "int32"
            }
          }
        ],
        "responses": {
          "200": {
            "description": "Success"
          }
        }
      }
    },
    "/api/Location/getalllocations": {
      "get": {
        "tags": [
          "Location"
        ],
        "responses": {
          "200": {
            "description": "Success"
          }
        }
      }
    },
    "/api/Location/getlocationbyid/{id}": {
      "get": {
        "tags": [
          "Location"
        ],
        "parameters": [
          {
            "name": "id",
            "in": "path",
            "required": true,
            "schema": {
              "type": "integer",
              "format": "int32"
            }
          }
        ],
        "responses": {
          "200": {
            "description": "Success"
          }
        }
      }
    },
    "/api/Location/addlocations": {
      "post": {
        "tags": [
          "Location"
        ],
        "requestBody": {
          "content": {
            "application/json": {
              "schema": {
                "$ref": "#/components/schemas/Location"
              }
            },
            "text/json": {
              "schema": {
                "$ref": "#/components/schemas/Location"
              }
            },
            "application/*+json": {
              "schema": {
                "$ref": "#/components/schemas/Location"
              }
            }
          }
        },
        "responses": {
          "200": {
            "description": "Success"
          }
        }
      }
    },
    "/api/Location/updatelocation/{id}": {
      "put": {
        "tags": [
          "Location"
        ],
        "parameters": [
          {
            "name": "id",
            "in": "path",
            "required": true,
            "schema": {
              "type": "integer",
              "format": "int32"
            }
          }
        ],
        "requestBody": {
          "content": {
            "application/json": {
              "schema": {
                "$ref": "#/components/schemas/Location"
              }
            },
            "text/json": {
              "schema": {
                "$ref": "#/components/schemas/Location"
              }
            },
            "application/*+json": {
              "schema": {
                "$ref": "#/components/schemas/Location"
              }
            }
          }
        },
        "responses": {
          "200": {
            "description": "Success"
          }
        }
      }
    },
    "/api/Location/deletelocation/{id}": {
      "delete": {
        "tags": [
          "Location"
        ],
        "parameters": [
          {
            "name": "id",
            "in": "path",
            "required": true,
            "schema": {
              "type": "integer",
              "format": "int32"
            }
          }
        ],
        "responses": {
          "200": {
            "description": "Success"
          }
        }
      }
    },
    "/api/State/getallstates": {
      "get": {
        "tags": [
          "State"
        ],
        "responses": {
          "200": {
            "description": "Success"
          }
        }
      }
    },
    "/api/State/getstatebyid/{id}": {
      "get": {
        "tags": [
          "State"
        ],
        "parameters": [
          {
            "name": "id",
            "in": "path",
            "required": true,
            "schema": {
              "type": "integer",
              "format": "int32"
            }
          }
        ],
        "responses": {
          "200": {
            "description": "Success"
          }
        }
      }
    },
    "/api/State/addstates": {
      "post": {
        "tags": [
          "State"
        ],
        "requestBody": {
          "content": {
            "application/json": {
              "schema": {
                "$ref": "#/components/schemas/State"
              }
            },
            "text/json": {
              "schema": {
                "$ref": "#/components/schemas/State"
              }
            },
            "application/*+json": {
              "schema": {
                "$ref": "#/components/schemas/State"
              }
            }
          }
        },
        "responses": {
          "200": {
            "description": "Success"
          }
        }
      }
    },
    "/api/State/updatestate/{id}": {
      "put": {
        "tags": [
          "State"
        ],
        "parameters": [
          {
            "name": "id",
            "in": "path",
            "required": true,
            "schema": {
              "type": "integer",
              "format": "int32"
            }
          }
        ],
        "requestBody": {
          "content": {
            "application/json": {
              "schema": {
                "$ref": "#/components/schemas/State"
              }
            },
            "text/json": {
              "schema": {
                "$ref": "#/components/schemas/State"
              }
            },
            "application/*+json": {
              "schema": {
                "$ref": "#/components/schemas/State"
              }
            }
          }
        },
        "responses": {
          "200": {
            "description": "Success"
          }
        }
      }
    },
    "/api/State/deletestate/{id}": {
      "delete": {
        "tags": [
          "State"
        ],
        "parameters": [
          {
            "name": "id",
            "in": "path",
            "required": true,
            "schema": {
              "type": "integer",
              "format": "int32"
            }
          }
        ],
        "responses": {
          "200": {
            "description": "Success"
          }
        }
      }
    },
    "/api/Student/getallstudents": {
      "get": {
        "tags": [
          "Student"
        ],
        "responses": {
          "200": {
            "description": "Success"
          }
        }
      }
    },
    "/api/Student/getstudentbyid/{id}": {
      "get": {
        "tags": [
          "Student"
        ],
        "parameters": [
          {
            "name": "id",
            "in": "path",
            "required": true,
            "schema": {
              "type": "integer",
              "format": "int32"
            }
          }
        ],
        "responses": {
          "200": {
            "description": "Success"
          }
        }
      }
    },
    "/api/Student/addstudent": {
      "post": {
        "tags": [
          "Student"
        ],
        "requestBody": {
          "content": {
            "application/json": {
              "schema": {
                "$ref": "#/components/schemas/StudentDto"
              }
            },
            "text/json": {
              "schema": {
                "$ref": "#/components/schemas/StudentDto"
              }
            },
            "application/*+json": {
              "schema": {
                "$ref": "#/components/schemas/StudentDto"
              }
            }
          }
        },
        "responses": {
          "200": {
            "description": "Success"
          }
        }
      }
    },
    "/api/Student/updatestudent/{id}": {
      "put": {
        "tags": [
          "Student"
        ],
        "parameters": [
          {
            "name": "id",
            "in": "path",
            "required": true,
            "schema": {
              "type": "integer",
              "format": "int32"
            }
          }
        ],
        "requestBody": {
          "content": {
            "application/json": {
              "schema": {
                "$ref": "#/components/schemas/StudentDto"
              }
            },
            "text/json": {
              "schema": {
                "$ref": "#/components/schemas/StudentDto"
              }
            },
            "application/*+json": {
              "schema": {
                "$ref": "#/components/schemas/StudentDto"
              }
            }
          }
        },
        "responses": {
          "200": {
            "description": "Success"
          }
        }
      }
    },
    "/api/Student/deletestudent/{id}": {
      "delete": {
        "tags": [
          "Student"
        ],
        "parameters": [
          {
            "name": "id",
            "in": "path",
            "required": true,
            "schema": {
              "type": "integer",
              "format": "int32"
            }
          }
        ],
        "responses": {
          "200": {
            "description": "Success"
          }
        }
      }
    },
    "/api/Subject/getallsubjects": {
      "get": {
        "tags": [
          "Subject"
        ],
        "responses": {
          "200": {
            "description": "Success"
          }
        }
      }
    },
    "/api/Subject/getsubjectbyid/{id}": {
      "get": {
        "tags": [
          "Subject"
        ],
        "parameters": [
          {
            "name": "id",
            "in": "path",
            "required": true,
            "schema": {
              "type": "integer",
              "format": "int32"
            }
          }
        ],
        "responses": {
          "200": {
            "description": "Success"
          }
        }
      }
    },
    "/api/Subject/addsubjects": {
      "post": {
        "tags": [
          "Subject"
        ],
        "requestBody": {
          "content": {
            "application/json": {
              "schema": {
                "$ref": "#/components/schemas/Subject"
              }
            },
            "text/json": {
              "schema": {
                "$ref": "#/components/schemas/Subject"
              }
            },
            "application/*+json": {
              "schema": {
                "$ref": "#/components/schemas/Subject"
              }
            }
          }
        },
        "responses": {
          "200": {
            "description": "Success"
          }
        }
      }
    },
    "/api/Subject/updatesubject/{id}": {
      "put": {
        "tags": [
          "Subject"
        ],
        "parameters": [
          {
            "name": "id",
            "in": "path",
            "required": true,
            "schema": {
              "type": "integer",
              "format": "int32"
            }
          }
        ],
        "requestBody": {
          "content": {
            "application/json": {
              "schema": {
                "$ref": "#/components/schemas/Subject"
              }
            },
            "text/json": {
              "schema": {
                "$ref": "#/components/schemas/Subject"
              }
            },
            "application/*+json": {
              "schema": {
                "$ref": "#/components/schemas/Subject"
              }
            }
          }
        },
        "responses": {
          "200": {
            "description": "Success"
          }
        }
      }
    },
    "/api/Subject/deletesubject/{id}": {
      "delete": {
        "tags": [
          "Subject"
        ],
        "parameters": [
          {
            "name": "id",
            "in": "path",
            "required": true,
            "schema": {
              "type": "integer",
              "format": "int32"
            }
          }
        ],
        "responses": {
          "200": {
            "description": "Success"
          }
        }
      }
    },
    "/api/Teacher/getallteachers": {
      "get": {
        "tags": [
          "Teacher"
        ],
        "responses": {
          "200": {
            "description": "Success"
          }
        }
      }
    },
    "/api/Teacher/getteacherbyid/{id}": {
      "get": {
        "tags": [
          "Teacher"
        ],
        "parameters": [
          {
            "name": "id",
            "in": "path",
            "required": true,
            "schema": {
              "type": "integer",
              "format": "int32"
            }
          }
        ],
        "responses": {
          "200": {
            "description": "Success"
          }
        }
      }
    },
    "/api/Teacher/addteacher": {
      "post": {
        "tags": [
          "Teacher"
        ],
        "requestBody": {
          "content": {
            "application/json": {
              "schema": {
                "$ref": "#/components/schemas/TeacherDto"
              }
            },
            "text/json": {
              "schema": {
                "$ref": "#/components/schemas/TeacherDto"
              }
            },
            "application/*+json": {
              "schema": {
                "$ref": "#/components/schemas/TeacherDto"
              }
            }
          }
        },
        "responses": {
          "200": {
            "description": "Success"
          }
        }
      }
    },
    "/api/Teacher/updateteacher/{id}": {
      "put": {
        "tags": [
          "Teacher"
        ],
        "parameters": [
          {
            "name": "id",
            "in": "path",
            "required": true,
            "schema": {
              "type": "integer",
              "format": "int32"
            }
          }
        ],
        "requestBody": {
          "content": {
            "application/json": {
              "schema": {
                "$ref": "#/components/schemas/TeacherDto"
              }
            },
            "text/json": {
              "schema": {
                "$ref": "#/components/schemas/TeacherDto"
              }
            },
            "application/*+json": {
              "schema": {
                "$ref": "#/components/schemas/TeacherDto"
              }
            }
          }
        },
        "responses": {
          "200": {
            "description": "Success"
          }
        }
      }
    },
    "/api/Teacher/deleteteacher/{id}": {
      "delete": {
        "tags": [
          "Teacher"
        ],
        "parameters": [
          {
            "name": "id",
            "in": "path",
            "required": true,
            "schema": {
              "type": "integer",
              "format": "int32"
            }
          }
        ],
        "responses": {
          "200": {
            "description": "Success"
          }
        }
      }
    },
    "/api/Vehicle/getallvehicles": {
      "get": {
        "tags": [
          "Vehicle"
        ],
        "responses": {
          "200": {
            "description": "Success"
          }
        }
      }
    },
    "/api/Vehicle/getvehiclebyid/{id}": {
      "get": {
        "tags": [
          "Vehicle"
        ],
        "parameters": [
          {
            "name": "id",
            "in": "path",
            "required": true,
            "schema": {
              "type": "integer",
              "format": "int32"
            }
          }
        ],
        "responses": {
          "200": {
            "description": "Success"
          }
        }
      }
    },
    "/api/Vehicle/addvehicles": {
      "post": {
        "tags": [
          "Vehicle"
        ],
        "requestBody": {
          "content": {
            "application/json": {
              "schema": {
                "$ref": "#/components/schemas/Vehicle"
              }
            },
            "text/json": {
              "schema": {
                "$ref": "#/components/schemas/Vehicle"
              }
            },
            "application/*+json": {
              "schema": {
                "$ref": "#/components/schemas/Vehicle"
              }
            }
          }
        },
        "responses": {
          "200": {
            "description": "Success"
          }
        }
      }
    },
    "/api/Vehicle/updatevehicle/{id}": {
      "put": {
        "tags": [
          "Vehicle"
        ],
        "parameters": [
          {
            "name": "id",
            "in": "path",
            "required": true,
            "schema": {
              "type": "integer",
              "format": "int32"
            }
          }
        ],
        "requestBody": {
          "content": {
            "application/json": {
              "schema": {
                "$ref": "#/components/schemas/Vehicle"
              }
            },
            "text/json": {
              "schema": {
                "$ref": "#/components/schemas/Vehicle"
              }
            },
            "application/*+json": {
              "schema": {
                "$ref": "#/components/schemas/Vehicle"
              }
            }
          }
        },
        "responses": {
          "200": {
            "description": "Success"
          }
        }
      }
    },
    "/api/Vehicle/deletevehicle/{id}": {
      "delete": {
        "tags": [
          "Vehicle"
        ],
        "parameters": [
          {
            "name": "id",
            "in": "path",
            "required": true,
            "schema": {
              "type": "integer",
              "format": "int32"
            }
          }
        ],
        "responses": {
          "200": {
            "description": "Success"
          }
        }
      }
    },
    "/WeatherForecast": {
      "get": {
        "tags": [
          "WeatherForecast"
        ],
        "operationId": "GetWeatherForecast",
        "responses": {
          "200": {
            "description": "Success",
            "content": {
              "text/plain": {
                "schema": {
                  "type": "array",
                  "items": {
                    "$ref": "#/components/schemas/WeatherForecast"
                  }
                }
              },
              "application/json": {
                "schema": {
                  "type": "array",
                  "items": {
                    "$ref": "#/components/schemas/WeatherForecast"
                  }
                }
              },
              "text/json": {
                "schema": {
                  "type": "array",
                  "items": {
                    "$ref": "#/components/schemas/WeatherForecast"
                  }
                }
              }
            }
          }
        }
      }
    }
  },
  "components": {
    "schemas": {
      "Club": {
        "required": [
          "clubName"
        ],
        "type": "object",
        "properties": {
          "clubId": {
            "type": "integer",
            "format": "int32"
          },
          "clubName": {
            "minLength": 1,
            "type": "string"
          },
          "students": {
            "type": "array",
            "items": {
              "$ref": "#/components/schemas/Student"
            },
            "nullable": true
          }
        },
        "additionalProperties": false
      },
      "DateOnly": {
        "type": "object",
        "properties": {
          "year": {
            "type": "integer",
            "format": "int32"
          },
          "month": {
            "type": "integer",
            "format": "int32"
          },
          "day": {
            "type": "integer",
            "format": "int32"
          },
          "dayOfWeek": {
            "$ref": "#/components/schemas/DayOfWeek"
          },
          "dayOfYear": {
            "type": "integer",
            "format": "int32",
            "readOnly": true
          },
          "dayNumber": {
            "type": "integer",
            "format": "int32",
            "readOnly": true
          }
        },
        "additionalProperties": false
      },
      "DayOfWeek": {
        "enum": [
          0,
          1,
          2,
          3,
          4,
          5,
          6
        ],
        "type": "integer",
        "format": "int32"
      },
      "Department": {
        "type": "object",
        "properties": {
          "departmentId": {
            "type": "integer",
            "format": "int32"
          },
          "departmentName": {
            "type": "string",
            "nullable": true
          }
        },
        "additionalProperties": false
      },
      "EmployeeCategory": {
        "type": "object",
        "properties": {
          "categoryId": {
            "type": "integer",
            "format": "int32"
          },
          "categoryName": {
            "type": "string",
            "nullable": true
          }
        },
        "additionalProperties": false
      },
      "EmployeeDto": {
        "type": "object",
        "properties": {
          "employeeId": {
            "type": "integer",
            "format": "int32"
          },
          "employeeName": {
            "type": "string",
            "nullable": true
          },
          "email": {
            "type": "string",
            "nullable": true
          },
          "mobile": {
            "type": "string",
            "nullable": true
          },
          "gender": {
            "type": "string",
            "nullable": true
          },
          "addressLine1": {
            "type": "string",
            "nullable": true
          },
          "addressLine2": {
            "type": "string",
            "nullable": true
          },
          "locationId": {
            "type": "integer",
            "format": "int32"
          },
          "stateId": {
            "type": "integer",
            "format": "int32"
          },
          "dateOfBirth": {
            "type": "string",
            "format": "date-time"
          },
          "categoryId": {
            "type": "integer",
            "format": "int32"
          },
          "departmentId": {
            "type": "integer",
            "format": "int32"
          },
          "subjectId": {
            "type": "integer",
            "format": "int32"
          },
          "clubId": {
            "type": "integer",
            "format": "int32"
          }
        },
        "additionalProperties": false
      },
      "Location": {
        "type": "object",
        "properties": {
          "locationId": {
            "type": "integer",
            "format": "int32"
          },
          "locationCode": {
            "type": "string",
            "nullable": true
          },
          "locationName": {
            "type": "string",
            "nullable": true
          },
          "stateId": {
            "type": "integer",
            "format": "int32"
          },
          "state": {
            "$ref": "#/components/schemas/State"
          }
        },
        "additionalProperties": false
      },
      "State": {
        "type": "object",
        "properties": {
          "stateId": {
            "type": "integer",
            "format": "int32"
          },
          "stateCode": {
            "type": "string",
            "nullable": true
          },
          "stateName": {
            "type": "string",
            "nullable": true
          }
        },
        "additionalProperties": false
      },
      "Student": {
        "required": [
          "email",
          "gender",
          "studentName"
        ],
        "type": "object",
        "properties": {
          "studentId": {
            "type": "integer",
            "format": "int32"
          },
          "rollNumber": {
            "type": "string",
            "nullable": true
          },
          "studentName": {
            "maxLength": 100,
            "minLength": 0,
            "type": "string"
          },
          "email": {
            "minLength": 1,
            "type": "string",
            "format": "email"
          },
          "mobile": {
            "type": "string",
            "format": "tel",
            "nullable": true
          },
          "gender": {
            "maxLength": 10,
            "minLength": 0,
            "type": "string"
          },
          "address": {
            "maxLength": 500,
            "minLength": 0,
            "type": "string",
            "nullable": true
          },
          "dateOfBirth": {
            "type": "string",
            "format": "date"
          },
          "guardian": {
            "type": "string",
            "nullable": true
          },
          "className": {
            "type": "string",
            "nullable": true
          },
          "clubId": {
            "type": "integer",
            "format": "int32"
          }
        },
        "additionalProperties": false
      },
      "StudentDto": {
        "required": [
          "clubId",
          "email",
          "studentName"
        ],
        "type": "object",
        "properties": {
          "studentId": {
            "type": "integer",
            "format": "int32"
          },
          "studentName": {
            "minLength": 1,
            "type": "string"
          },
          "email": {
            "minLength": 1,
            "type": "string",
            "format": "email"
          },
          "mobile": {
            "type": "string",
            "format": "tel",
            "nullable": true
          },
          "gender": {
            "type": "string",
            "nullable": true
          },
          "address": {
            "type": "string",
            "nullable": true
          },
          "dateOfBirth": {
            "type": "string",
            "format": "date-time"
          },
          "guardian": {
            "type": "string",
            "nullable": true
          },
          "className": {
            "type": "string",
            "nullable": true
          },
          "clubId": {
            "type": "integer",
            "format": "int32"
          }
        },
        "additionalProperties": false
      },
      "Subject": {
        "type": "object",
        "properties": {
          "subjectId": {
            "type": "integer",
            "format": "int32"
          },
          "subjectName": {
            "type": "string",
            "nullable": true
          }
        },
        "additionalProperties": false
      },
      "TeacherDto": {
        "type": "object",
        "properties": {
          "employeeId": {
            "type": "integer",
            "format": "int32"
          },
          "teacherName": {
            "type": "string",
            "nullable": true
          },
          "email": {
            "type": "string",
            "nullable": true
          },
          "mobile": {
            "type": "string",
            "nullable": true
          },
          "gender": {
            "type": "string",
            "nullable": true
          },
          "addressLine1": {
            "type": "string",
            "nullable": true
          },
          "addressLine2": {
            "type": "string",
            "nullable": true
          },
          "locationId": {
            "type": "integer",
            "format": "int32"
          },
          "stateId": {
            "type": "integer",
            "format": "int32"
          },
          "dateOfBirth": {
            "type": "string",
            "format": "date-time"
          },
          "categoryId": {
            "type": "integer",
            "format": "int32"
          },
          "departmentId": {
            "type": "integer",
            "format": "int32"
          },
          "subjectId": {
            "type": "integer",
            "format": "int32"
          },
          "clubId": {
            "type": "integer",
            "format": "int32"
          }
        },
        "additionalProperties": false
      },
      "Vehicle": {
        "type": "object",
        "properties": {
          "vehicleId": {
            "type": "integer",
            "format": "int32"
          },
          "vehicleNumber": {
            "type": "string",
            "nullable": true
          }
        },
        "additionalProperties": false
      },
      "WeatherForecast": {
        "type": "object",
        "properties": {
          "date": {
            "$ref": "#/components/schemas/DateOnly"
          },
          "temperatureC": {
            "type": "integer",
            "format": "int32"
          },
          "temperatureF": {
            "type": "integer",
            "format": "int32",
            "readOnly": true
          },
          "summary": {
            "type": "string",
            "nullable": true
          }
        },
        "additionalProperties": false
      }
    }
  }
}